README.md
setup.py
promregapi/__init__.py
promregapi/promregapi.py
promregapi.egg-info/PKG-INFO
promregapi.egg-info/SOURCES.txt
promregapi.egg-info/dependency_links.txt
promregapi.egg-info/requires.txt
promregapi.egg-info/top_level.txt