Metadata-Version: 1.1
Name: promregapi
Version: 0.1.0
Summary: Python API for Prometheus Registration
Home-page: https://github.com/Teszko/promreg-api
Author: Henryk Iwaniuk
Author-email: iwaniuk@tu-berlin.de
License: https://raw.githubusercontent.com/Teszko/promreg-api/master/LICENSE
Download-URL: https://github.com/Teszko/promreg-api/releases/download/0.1/promreg-api-0.1.tar.gz
Keywords: promreg prometheus
Platform: Posix; MacOS X; Windows
Classifier: Development Status :: 4 - Beta
Classifier: Intended Audience :: Developers
Classifier: Topic :: Software Development :: Libraries
Classifier: License :: OSI Approved :: MIT License
Classifier: Programming Language :: Python :: 3
Classifier: Programming Language :: Python :: 3.4
Classifier: Programming Language :: Python :: 3.5
Classifier: Programming Language :: Python :: 3.6
Classifier: Programming Language :: Python :: 3.7
Classifier: Programming Language :: Python :: 3.8
